{
  "santabaRelease": 150,
  "widgetTokens": [],
  "name": "Kubernetes Deployments",
  "description": "",
  "overwriteGroupFields": false,
  "widgetsConfigVersion": 2,
  "type": "dashboard",
  "widgets": [
    {
      "position": {
        "col": 1,
        "sizex": 12,
        "row": 1,
        "sizey": 2
      },
      "config": {
        "ackChecked": true,
        "displaySettings": {
          "showTypeIcon": false,
          "displayAs": "table"
        },
        "displayWarnAlert": true,
        "description": "",
        "type": "noc",
        "version": 2,
        "displayErrorAlert": true,
        "displayColumn": 7,
        "name": "Kubernetes Deployment Alert Status",
        "displayCriticalAlert": true,
        "theme": "newSolidDarkBlue",
        "interval": 3,
        "sortBy": "alertSeverity",
        "timescale": "day",
        "sdtChecked": true,
        "items": [{
          "dataPointName": "*",
          "instanceName": "*",
          "name": "##RESOURCENAME##",
          "dataSourceDisplayName": "Kubernetes Deployment",
          "groupBy": "device",
          "type": "device",
          "deviceGroupFullPath": "##defaultResourceGroup##",
          "deviceDisplayName": "*"
        }]
      }
    },
    {
      "position": {
        "col": 11,
        "sizex": 2,
        "row": 3,
        "sizey": 2
      },
      "config": {
        "bigNumberInfo": {
          "virtualDataPoints": [],
          "counters": [],
          "dataPoints": [
            {
              "dataPointName": "availablePods",
              "instanceName": "*",
              "dataSourceFullName": "Kubernetes Deployment (Kubernetes_Deployment)",
              "name": "availablePods",
              "aggregateFunction": "SUM",
              "deviceGroupFullPath": "##defaultResourceGroup##",
              "deviceDisplayName": "*"
            },
            {
              "dataPointName": "readyPods",
              "instanceName": "*",
              "dataSourceFullName": "Kubernetes Deployment (Kubernetes_Deployment)",
              "name": "readyPods",
              "aggregateFunction": "SUM",
              "deviceGroupFullPath": "##defaultResourceGroup##",
              "deviceDisplayName": "*"
            },
            {
              "dataPointName": "unavailablePods",
              "instanceName": "*",
              "dataSourceFullName": "Kubernetes Deployment (Kubernetes_Deployment)",
              "name": "unavailablePods",
              "aggregateFunction": "SUM",
              "deviceGroupFullPath": "##defaultResourceGroup##",
              "deviceDisplayName": "*"
            }
          ],
          "bigNumberItems": [{
            "dataPointName": "availablePods",
            "useCommaSeparators": false,
            "bottomLabel": "",
            "rounding": 0,
            "position": 1,
            "rightLabel": "Available Pods (Aggregate)",
            "colorThresholds": null
          }]
        },
        "displaySettings": {},
        "name": "Deployment Stats",
        "description": "",
        "theme": "newSolidDarkBlue",
        "interval": 3,
        "type": "bigNumber",
        "timescale": "day",
        "version": 2
      }
    },
    {
      "position": {
        "col": 11,
        "sizex": 2,
        "row": 7,
        "sizey": 2
      },
      "config": {
        "bigNumberInfo": {
          "virtualDataPoints": [],
          "counters": [],
          "dataPoints": [
            {
              "dataPointName": "availablePods",
              "instanceName": "*",
              "dataSourceFullName": "Kubernetes Deployment (Kubernetes_Deployment)",
              "name": "availablePods",
              "aggregateFunction": "SUM",
              "deviceGroupFullPath": "##defaultResourceGroup##",
              "deviceDisplayName": "*"
            },
            {
              "dataPointName": "readyPods",
              "instanceName": "*",
              "dataSourceFullName": "Kubernetes Deployment (Kubernetes_Deployment)",
              "name": "readyPods",
              "aggregateFunction": "SUM",
              "deviceGroupFullPath": "##defaultResourceGroup##",
              "deviceDisplayName": "*"
            },
            {
              "dataPointName": "unavailablePods",
              "instanceName": "*",
              "dataSourceFullName": "Kubernetes Deployment (Kubernetes_Deployment)",
              "name": "unavailablePods",
              "aggregateFunction": "SUM",
              "deviceGroupFullPath": "##defaultResourceGroup##",
              "deviceDisplayName": "*"
            }
          ],
          "bigNumberItems": [{
            "dataPointName": "unavailablePods",
            "useCommaSeparators": false,
            "bottomLabel": "",
            "rounding": 0,
            "position": 1,
            "rightLabel": "Unavailable Pods (Aggregate)",
            "colorThresholds": null
          }]
        },
        "displaySettings": {},
        "name": "Deployment Stats",
        "description": "",
        "theme": "newSolidDarkBlue",
        "interval": 3,
        "type": "bigNumber",
        "timescale": "day",
        "version": 2
      }
    },
    {
      "position": {
        "col": 11,
        "sizex": 2,
        "row": 5,
        "sizey": 2
      },
      "config": {
        "bigNumberInfo": {
          "virtualDataPoints": [],
          "counters": [],
          "dataPoints": [
            {
              "dataPointName": "availablePods",
              "instanceName": "*",
              "dataSourceFullName": "Kubernetes Deployment (Kubernetes_Deployment)",
              "name": "availablePods",
              "aggregateFunction": "SUM",
              "deviceGroupFullPath": "##defaultResourceGroup##",
              "deviceDisplayName": "*"
            },
            {
              "dataPointName": "readyPods",
              "instanceName": "*",
              "dataSourceFullName": "Kubernetes Deployment (Kubernetes_Deployment)",
              "name": "readyPods",
              "aggregateFunction": "SUM",
              "deviceGroupFullPath": "##defaultResourceGroup##",
              "deviceDisplayName": "*"
            },
            {
              "dataPointName": "unavailablePods",
              "instanceName": "*",
              "dataSourceFullName": "Kubernetes Deployment (Kubernetes_Deployment)",
              "name": "unavailablePods",
              "aggregateFunction": "SUM",
              "deviceGroupFullPath": "##defaultResourceGroup##",
              "deviceDisplayName": "*"
            }
          ],
          "bigNumberItems": [{
            "dataPointName": "readyPods",
            "useCommaSeparators": false,
            "bottomLabel": "",
            "rounding": 0,
            "position": 1,
            "rightLabel": "Ready Pods (Aggregate)",
            "colorThresholds": null
          }]
        },
        "displaySettings": {},
        "name": "Deployment Stats",
        "description": "",
        "theme": "newSolidDarkBlue",
        "interval": 3,
        "type": "bigNumber",
        "timescale": "day",
        "version": 2
      }
    },
    {
      "position": {
        "col": 1,
        "sizex": 12,
        "row": 12,
        "sizey": 4
      },
      "config": {
        "displaySettings": {
          "isShowAll": false,
          "showFilter": false,
          "columns": [
            {
              "visible": false,
              "columnLabel": "Severity",
              "columnKey": "alert-severity"
            },
            {
              "visible": true,
              "columnLabel": "Began",
              "columnKey": "alert-began"
            },
            {
              "visible": true,
              "columnLabel": "Resource/Website",
              "columnKey": "alert-device"
            },
            {
              "visible": true,
              "columnLabel": "LogicModule",
              "columnKey": "alert-datasource"
            },
            {
              "visible": true,
              "columnLabel": "Instance",
              "columnKey": "alert-datasource-instance"
            },
            {
              "visible": true,
              "columnLabel": "Datapoint",
              "columnKey": "alert-datapoint"
            },
            {
              "visible": true,
              "columnLabel": "Value",
              "columnKey": "alert-value"
            },
            {
              "visible": true,
              "columnLabel": "Static Threshold",
              "columnKey": "alert-static-threshold"
            },
            {
              "visible": true,
              "columnLabel": "Dynamic Threshold",
              "columnKey": "alert-dynamic-threshold"
            },
            {
              "visible": false,
              "columnLabel": "Group",
              "columnKey": "alert-group"
            },
            {
              "visible": false,
              "columnLabel": "Notes",
              "columnKey": "alert-notes"
            },
            {
              "visible": false,
              "columnLabel": "Acknowledged By",
              "columnKey": "alert-acked-by"
            },
            {
              "visible": false,
              "columnLabel": "Acknowledged On",
              "columnKey": "alert-acked-on"
            },
            {
              "visible": false,
              "columnLabel": "Cleared On",
              "columnKey": "alert-cleared-on"
            },
            {
              "visible": false,
              "columnLabel": "In SDT",
              "columnKey": "alert-in-sdt"
            },
            {
              "visible": false,
              "columnLabel": "Alert Rule",
              "columnKey": "alert-rule-name"
            },
            {
              "visible": false,
              "columnLabel": "Escalation Chain",
              "columnKey": "alert-escalation-chain"
            },
            {
              "visible": false,
              "columnLabel": "Instance Description",
              "columnKey": "alert-datasource-instance-description"
            },
            {
              "visible": false,
              "columnLabel": "Full Path",
              "columnKey": "alert-full-path"
            },
            {
              "visible": false,
              "columnLabel": "Routing State",
              "columnKey": "alert-routing-state"
            },
            {
              "visible": false,
              "columnLabel": "Dependency Role",
              "columnKey": "alert-dependency-role"
            },
            {
              "visible": false,
              "columnLabel": "Dependent Alerts",
              "columnKey": "alert-dependent-alerts"
            }
          ],
          "playSound": {},
          "fontsize": "normal-font",
          "sort": "-startEpoch"
        },
        "name": "Kubernetes Deployments Alert Detail",
        "description": "",
        "theme": "newSolidDarkBlue",
        "interval": 3,
        "filters": {
          "severity": "",
          "sdted": "all",
          "chain": "",
          "instance": "",
          "dataPoint": "",
          "rule": "",
          "acked": "all",
          "dependencyRoutingState": "",
          "dependencyRole": "",
          "host": "",
          "keyword": "",
          "dataSource": "Kubernetes%20Deployment",
          "cleared": "no",
          "group": "%23%23defaultResourceGroup%23%23*"
        },
        "type": "alert",
        "timescale": "day",
        "version": 2
      }
    },
    {
      "position": {
        "col": 5,
        "sizex": 6,
        "row": 3,
        "sizey": 3
      },
      "config": {
        "displaySettings": {},
        "name": "Top Kubernetes Deployments by Ready Pods (Trend)",
        "description": "",
        "theme": "newBorderDarkBlue",
        "interval": 3,
        "graphInfo": {
          "virtualDataPoints": [],
          "minValue": 0,
          "topX": 25,
          "maxValue": "NaN",
          "dataPoints": [{
            "dataPointName": "readyPods",
            "instanceName": {
              "isGlob": true,
              "value": "*"
            },
            "dataSourceFullName": "Kubernetes Deployment (Kubernetes_Deployment)",
            "consolidateFunction": "average",
            "display": {
              "color": "Auto",
              "legend": "##RESOURCENAME## ready",
              "type": "stack",
              "option": "custom"
            },
            "name": "readyPods",
            "aggregateFunction": "SUM",
            "deviceDisplayName": {
              "isGlob": true,
              "value": "*"
            },
            "deviceGroupFullPath": {
              "isGlob": true,
              "value": "##defaultResourceGroup##"
            }
          }],
          "verticalLabel": "pods",
          "aggregate": false,
          "desc": true,
          "scaleUnit": 1000,
          "globalConsolidateFunction": "VaST"
        },
        "type": "cgraph",
        "timescale": "2days",
        "version": 2
      }
    },
    {
      "position": {
        "col": 5,
        "sizex": 6,
        "row": 6,
        "sizey": 3
      },
      "config": {
        "displaySettings": {},
        "name": "Top Kubernetes Deployments by Unavailable Pods (Trend)",
        "description": "",
        "theme": "newBorderDarkBlue",
        "interval": 3,
        "graphInfo": {
          "virtualDataPoints": [],
          "minValue": 0,
          "topX": 10,
          "maxValue": "NaN",
          "dataPoints": [{
            "dataPointName": "unavailablePods",
            "instanceName": {
              "isGlob": true,
              "value": "*"
            },
            "dataSourceFullName": "Kubernetes Deployment (Kubernetes_Deployment)",
            "consolidateFunction": "average",
            "display": {
              "color": "Auto",
              "legend": "##RESOURCENAME## unavailable",
              "type": "stack",
              "option": "custom"
            },
            "name": "unavailablePods",
            "aggregateFunction": "SUM",
            "deviceDisplayName": {
              "isGlob": true,
              "value": "*"
            },
            "deviceGroupFullPath": {
              "isGlob": true,
              "value": "##defaultResourceGroup##"
            }
          }],
          "verticalLabel": "pods",
          "aggregate": false,
          "desc": true,
          "scaleUnit": 1000,
          "globalConsolidateFunction": "VaST"
        },
        "type": "cgraph",
        "timescale": "2days",
        "version": 2
      }
    },
    {
      "position": {
        "col": 1,
        "sizex": 4,
        "row": 3,
        "sizey": 6
      },
      "config": {
        "displaySettings": {"pageSize": "15"},
        "columns": [
          {
            "rpn": "",
            "dataPointName": "readyPods",
            "displayType": "raw",
            "minValue": 0,
            "unitLabel": " pods",
            "maxValue": 100,
            "colorThresholds": [],
            "columnName": "Ready",
            "enableForecast": false,
            "roundingDecimal": 2
          },
          {
            "rpn": "",
            "dataPointName": "availablePods",
            "displayType": "raw",
            "minValue": 0,
            "unitLabel": " pods",
            "maxValue": 100,
            "colorThresholds": [],
            "columnName": "Available",
            "enableForecast": false,
            "roundingDecimal": 2
          },
          {
            "rpn": "",
            "dataPointName": "unavailablePods",
            "displayType": "raw",
            "minValue": 0,
            "unitLabel": " pods",
            "maxValue": 100,
            "colorThresholds": [],
            "columnName": "Unavailable",
            "enableForecast": false,
            "roundingDecimal": 2
          }
        ],
        "description": "",
        "forecast": {
          "severity": "warn",
          "confidence": 70,
          "timeRange": "Last 30 days",
          "algorithm": "Linear"
        },
        "type": "dynamicTable",
        "rows": [{
          "instanceName": "*",
          "label": "##RESOURCENAME##",
          "deviceDisplayName": "*",
          "groupFullPath": "##defaultResourceGroup##"
        }],
        "version": 2,
        "topX": 25,
        "dataSourceFullName": "Kubernetes Deployment (Kubernetes_Deployment)",
        "sortOrder": "descending",
        "name": "Kubernetes Deployment Statistics",
        "theme": "newSolidDarkBlue",
        "interval": 3,
        "timescale": "day"
      }
    }
  ],
  "version": 2
}